corgie/__init__.py
corgie/argparsers.py
corgie/block.py
corgie/boundingcube.py
corgie/constants.py
corgie/exceptions.py
corgie/helpers.py
corgie/log.py
corgie/main.py
corgie/mipless_cloudvolume.py
corgie/residuals.py
corgie/scheduling.py
corgie/spec.py
corgie/stack.py
corgie/worker.py
corgie/cli/__init__.py
corgie/cli/align.py
corgie/cli/align_block.py
corgie/cli/apply_processor.py
corgie/cli/apply_processor_by_spec.py
corgie/cli/broadcast.py
corgie/cli/combine_masks.py
corgie/cli/compare_sections.py
corgie/cli/compute_field.py
corgie/cli/compute_field_by_spec.py
corgie/cli/compute_stats.py
corgie/cli/copy.py
corgie/cli/create_segmentation_masks.py
corgie/cli/create_skeletons.py
corgie/cli/downsample.py
corgie/cli/downsample_by_spec.py
corgie/cli/fill_nearest.py
corgie/cli/filter_skeletons.py
corgie/cli/invert_field.py
corgie/cli/merge_copy.py
corgie/cli/merge_render.py
corgie/cli/multi_section_compare.py
corgie/cli/normalize.py
corgie/cli/normalize_by_spec.py
corgie/cli/old_compute_field.py
corgie/cli/render.py
corgie/cli/seethrough.py
corgie/cli/transform_skeletons.py
corgie/cli/upsample.py
corgie/cli/vote.py
corgie/cli/common/__init__.py
corgie/cli/common/chunked_job.py
corgie/data_backends/__init__.py
corgie/data_backends/base.py
corgie/data_backends/cv.py
corgie/data_backends/json.py
corgie/layers/__init__.py
corgie/layers/base.py
corgie/layers/volumetric_layers.py
corgie-0.1.1.dist-info/LICENSE
corgie-0.1.1.dist-info/METADATA
corgie-0.1.1.dist-info/WHEEL
corgie-0.1.1.dist-info/entry_points.txt
corgie-0.1.1.dist-info/top_level.txt
corgie-0.1.1.dist-info/RECORD
