Metadata-Version: 2.1
Name: corgie
Version: 0.1.1
Summary: Connectomics Registration General Inference Engine
Home-page: https://github.com/supersergiy/corgie
Author: Sergiy Popovych
Author-email: sergiy.popovich@gmail.com
License: UNKNOWN
Platform: UNKNOWN
Requires-Python: >=3.7
License-File: LICENSE
Requires-Dist: sphinx-click
Requires-Dist: torchfields
Requires-Dist: torch
Requires-Dist: gevent
Requires-Dist: torchvision
Requires-Dist: numpy
Requires-Dist: six
Requires-Dist: pyyaml
Requires-Dist: mazepa (>=0.1.1)
Requires-Dist: modelhouse (>=0.1.2)
Requires-Dist: click-option-group
Requires-Dist: click (<8,>=7)
Requires-Dist: procspec
Requires-Dist: idna (>=2.5)
Requires-Dist: google-auth (>=1.11.0)
Requires-Dist: cloud-volume
Requires-Dist: scikit-image
Requires-Dist: h5py
Requires-Dist: kimimaro
Requires-Dist: docutils (<0.18)
Requires-Dist: cloud-files
